Metadata-Version: 2.1
Name: sigtech
Version: 0.8.0
Summary: SigTech Python SDK
Author-email: SigTech <support@sigtech.com>
License: MIT
Project-URL: Homepage, https://github.com/SIGTechnologies/sigtech-python
Keywords: SIGTECH,FINANCE,TRADING,BACKTEST,QUANT
Classifier: Development Status :: 5 - Production/Stable
Classifier: Operating System :: OS Independent
Classifier: License :: OSI Approved :: MIT License
Classifier: Intended Audience :: Developers
Classifier: Intended Audience :: Financial and Insurance Industry
Classifier: Programming Language :: Python
Classifier: Programming Language :: Python :: 3
Classifier: Programming Language :: Python :: 3.6
Classifier: Programming Language :: Python :: 3.7
Classifier: Programming Language :: Python :: 3.8
Classifier: Programming Language :: Python :: 3.9
Classifier: Programming Language :: Python :: 3.10
Classifier: Programming Language :: Python :: 3.11
Classifier: Programming Language :: Python :: Implementation :: CPython
Requires-Python: >=3.6
License-File: LICENSE.txt
Requires-Dist: requests
Requires-Dist: pandas
Provides-Extra: test
Requires-Dist: jupyter ; extra == 'test'
Requires-Dist: matplotlib ; extra == 'test'
Requires-Dist: pytest ; extra == 'test'
Requires-Dist: statsmodels ; extra == 'test'
Provides-Extra: tools
Requires-Dist: autoflake ; extra == 'tools'
Requires-Dist: black ; extra == 'tools'
Requires-Dist: build ; extra == 'tools'
Requires-Dist: flake8 ; extra == 'tools'
Requires-Dist: isort ; extra == 'tools'
Requires-Dist: mypy ; extra == 'tools'
Requires-Dist: pandas-stubs ; extra == 'tools'
Requires-Dist: pytest ; extra == 'tools'
Requires-Dist: python-semantic-release <=7.34.6 ; extra == 'tools'
Requires-Dist: types-requests ; extra == 'tools'
Requires-Dist: types-jinja2 ; extra == 'tools'
